sm_translator/__init__.py
sm_translator/s_translator.py
selenium_translator-0.0.1.dist-info/METADATA
selenium_translator-0.0.1.dist-info/WHEEL
selenium_translator-0.0.1.dist-info/top_level.txt
selenium_translator-0.0.1.dist-info/RECORD
