Metadata-Version: 2.1
Name: selenium_translator
Version: 0.0.1
Requires-Dist: selenium
